kailash_nexus-1.1.3.dist-info/licenses/LICENSE
kailash_nexus-1.1.3.dist-info/licenses/NOTICE
nexus/__init__.py
nexus/channels.py
nexus/core.py
nexus/discovery.py
nexus/mcp_websocket_server.py
nexus/plugins.py
nexus/resources.py
nexus/validation.py
nexus/cli/__init__.py
nexus/cli/__main__.py
nexus/cli/main.py
nexus/mcp/__init__.py
nexus/mcp/server.py
nexus/mcp/transport.py
kailash_nexus-1.1.3.dist-info/METADATA
kailash_nexus-1.1.3.dist-info/WHEEL
kailash_nexus-1.1.3.dist-info/top_level.txt
kailash_nexus-1.1.3.dist-info/RECORD
