Metadata-Version: 2.4
Name: kailash-nexus
Version: 1.1.3
Summary: Zero-configuration multi-channel workflow orchestration platform
Author: Kailash Team
Author-email: info@integrum.com
License: Apache-2.0 WITH Additional-Terms
Keywords: workflow,orchestration,automation,api,cli,mcp
Classifier: Development Status :: 5 - Production/Stable
Classifier: Intended Audience :: Developers
Classifier: License :: OSI Approved :: Apache Software License
Classifier: Programming Language :: Python :: 3
Classifier: Programming Language :: Python :: 3.11
Classifier: Programming Language :: Python :: 3.12
Classifier: Programming Language :: Python :: 3.13
Classifier: Topic :: Software Development :: Libraries :: Python Modules
Classifier: Topic :: System :: Distributed Computing
Requires-Python: >=3.11
License-File: LICENSE
License-File: NOTICE
Requires-Dist: kailash>=0.9.31
Provides-Extra: dev
Requires-Dist: pytest>=7.0; extra == "dev"
Requires-Dist: pytest-asyncio>=0.21; extra == "dev"
Requires-Dist: pytest-cov>=4.0; extra == "dev"
Requires-Dist: requests>=2.28; extra == "dev"
Dynamic: author-email
Dynamic: license-file
Dynamic: requires-python
